Workbook

Sheet Data
A1: Department | B1: Account | C1: Category | D1: Month | E1: Budget | F1: Actual | G1: Variance ($) | H1: Variance (%) | I1: Status
A2: Sales | B2: Revenue | C2: Income | D2: Jan | E2: 700000 | F2: 718000 | G2: =F2-E2 -> 18000 | H2: =IF(E2=0,"",(F2-E2)/E2) -> 0.025714286 | I2: =IF(C2="Income",IF(F2>=E2,"Favorable","Unfavorable"),IF(F2<=E2,"Favorable","Unfavorable")) -> Favorable
A3: Operations | B3: Cost of Goods Sold | C3: COGS | D3: Jan | E3: 230000 | F3: 238000 | G3: =F3-E3 -> 8000 | H3: =IF(E3=0,"",(F3-E3)/E3) -> 0.034782609 | I3: =IF(C3="Income",IF(F3>=E3,"Favorable","Unfavorable"),IF(F3<=E3,"Favorable","Unfavorable")) -> Unfavorable
A4: Marketing | B4: Digital Ads | C4: Opex | D4: Jan | E4: 80000 | F4: 91000 | G4: =F4-E4 -> 11000 | H4: =IF(E4=0,"",(F4-E4)/E4) -> 0.1375 | I4: =IF(C4="Income",IF(F4>=E4,"Favorable","Unfavorable"),IF(F4<=E4,"Favorable","Unfavorable")) -> Unfavorable
A5: Marketing | B5: Events | C5: Opex | D5: Jan | E5: 20000 | F5: 16000 | G5: =F5-E5 -> -4000 | H5: =IF(E5=0,"",(F5-E5)/E5) -> -0.2 | I5: =IF(C5="Income",IF(F5>=E5,"Favorable","Unfavorable"),IF(F5<=E5,"Favorable","Unfavorable")) -> Favorable
A6: Operations | B6: Store Labor | C6: Opex | D6: Jan | E6: 150000 | F6: 144000 | G6: =F6-E6 -> -6000 | H6: =IF(E6=0,"",(F6-E6)/E6) -> -0.04 | I6: =IF(C6="Income",IF(F6>=E6,"Favorable","Unfavorable"),IF(F6<=E6,"Favorable","Unfavorable")) -> Favorable
A7: Operations | B7: Rent | C7: Opex | D7: Jan | E7: 40000 | F7: 40000 | G7: =F7-E7 -> 0 | H7: =IF(E7=0,"",(F7-E7)/E7) -> 0 | I7: =IF(C7="Income",IF(F7>=E7,"Favorable","Unfavorable"),IF(F7<=E7,"Favorable","Unfavorable")) -> Favorable
A8: G&A | B8: Software | C8: Opex | D8: Jan | E8: 25000 | F8: 26500 | G8: =F8-E8 -> 1500 | H8: =IF(E8=0,"",(F8-E8)/E8) -> 0.06 | I8: =IF(C8="Income",IF(F8>=E8,"Favorable","Unfavorable"),IF(F8<=E8,"Favorable","Unfavorable")) -> Unfavorable
A9: G&A | B9: Salaries | C9: Opex | D9: Jan | E9: 60000 | F9: 60000 | G9: =F9-E9 -> 0 | H9: =IF(E9=0,"",(F9-E9)/E9) -> 0 | I9: =IF(C9="Income",IF(F9>=E9,"Favorable","Unfavorable"),IF(F9<=E9,"Favorable","Unfavorable")) -> Favorable
A10: Sales | B10: Revenue | C10: Income | D10: Feb | E10: 720000 | F10: 698000 | G10: =F10-E10 -> -22000 | H10: =IF(E10=0,"",(F10-E10)/E10) -> -0.030555556 | I10: =IF(C10="Income",IF(F10>=E10,"Favorable","Unfavorable"),IF(F10<=E10,"Favorable","Unfavorable")) -> Unfavorable
A11: Operations | B11: Cost of Goods Sold | C11: COGS | D11: Feb | E11: 236000 | F11: 232000 | G11: =F11-E11 -> -4000 | H11: =IF(E11=0,"",(F11-E11)/E11) -> -0.016949153 | I11: =IF(C11="Income",IF(F11>=E11,"Favorable","Unfavorable"),IF(F11<=E11,"Favorable","Unfavorable")) -> Favorable
A12: Marketing | B12: Digital Ads | C12: Opex | D12: Feb | E12: 85000 | F12: 99000 | G12: =F12-E12 -> 14000 | H12: =IF(E12=0,"",(F12-E12)/E12) -> 0.16470588 | I12: =IF(C12="Income",IF(F12>=E12,"Favorable","Unfavorable"),IF(F12<=E12,"Favorable","Unfavorable")) -> Unfavorable
A13: Marketing | B13: Events | C13: Opex | D13: Feb | E13: 20000 | F13: 22000 | G13: =F13-E13 -> 2000 | H13: =IF(E13=0,"",(F13-E13)/E13) -> 0.1 | I13: =IF(C13="Income",IF(F13>=E13,"Favorable","Unfavorable"),IF(F13<=E13,"Favorable","Unfavorable")) -> Unfavorable
... A25: G&A | B25: Salaries | C25: Opex | D25: Mar | E25: 60000 | F25: 62000 | G25: =F25-E25 -> 2000 | H25: =IF(E25=0,"",(F25-E25)/E25) -> 0.033333333 | I25: =IF(C25="Income",IF(F25>=E25,"Favorable","Unfavorable"),IF(F25<=E25,"Favorable","Unfavorable")) -> Unfavorable

Sheet Summary
A1: BrewMetrics Coffee Co. — Q1 Budget vs. Actual (P&L)
A2: All figures in USD. Variance = Actual − Budget. Status: Favorable / Unfavorable by line.
A4: Line Item | B4: Budget | C4: Actual | D4: Variance ($) | E4: Variance (%) | F4: Status | H4: Category | I4: Budget | J4: Actual
A5: Revenue | B5: =SUMIFS(Data!E:E,Data!C:C,"Income") -> 2160000 | C5: =SUMIFS(Data!F:F,Data!C:C,"Income") -> 2188000 | D5: =C5-B5 -> 28000 | E5: =IF(B5=0,"",(C5-B5)/B5) -> 0.012962963 | F5: =IF(C5>=B5,"Favorable","Unfavorable") -> Favorable | H5: Revenue | I5: =B5 -> 2160000 | J5: =C5 -> 2188000
A6: COGS | B6: =SUMIFS(Data!E:E,Data!C:C,"COGS") -> 709000 | C6: =SUMIFS(Data!F:F,Data!C:C,"COGS") -> 718000 | D6: =C6-B6 -> 9000 | E6: =IF(B6=0,"",(C6-B6)/B6) -> 0.012693935 | F6: =IF(C6<=B6,"Favorable","Unfavorable") -> Unfavorable | H6: COGS | I6: =B6 -> 709000 | J6: =C6 -> 718000
A7: Gross Profit | B7: =B5-B6 -> 1451000 | C7: =C5-C6 -> 1470000 | D7: =C7-B7 -> 19000 | E7: =IF(B7=0,"",(C7-B7)/B7) -> 0.013094418 | F7: =IF(C7>=B7,"Favorable","Unfavorable") -> Favorable | H7: Opex | I7: =B8 -> 1152000 | J7: =C8 -> 1181500
A8: Operating Expenses | B8: =SUMIFS(Data!E:E,Data!C:C,"Opex") -> 1152000 | C8: =SUMIFS(Data!F:F,Data!C:C,"Opex") -> 1181500 | D8: =C8-B8 -> 29500 | E8: =IF(B8=0,"",(C8-B8)/B8) -> 0.025607639 | F8: =IF(C8<=B8,"Favorable","Unfavorable") -> Unfavorable
A9: Operating Income | B9: =B7-B8 -> 299000 | C9: =C7-C8 -> 288500 | D9: =C9-B9 -> -10500 | E9: =IF(B9=0,"",(C9-B9)/B9) -> -0.035117057 | F9: =IF(C9>=B9,"Favorable","Unfavorable") -> Unfavorable
A10: Operating Margin % | B10: =B9/B5 -> 0.13842593 | C10: =C9/C5 -> 0.13185558 | D10: =C10-B10 -> -0.0065703501
A13: Revenue by Month
A14: Month | B14: Budget | C14: Actual | D14: Variance ($)
A15: Jan | B15: =SUMIFS(Data!E:E,Data!C:C,"Income",Data!D:D,"Jan") -> 700000 | C15: =SUMIFS(Data!F:F,Data!C:C,"Income",Data!D:D,"Jan") -> 718000 | D15: =C15-B15 -> 18000
A16: Feb | B16: =SUMIFS(Data!E:E,Data!C:C,"Income",Data!D:D,"Feb") -> 720000 | C16: =SUMIFS(Data!F:F,Data!C:C,"Income",Data!D:D,"Feb") -> 698000 | D16: =C16-B16 -> -22000
A17: Mar | B17: =SUMIFS(Data!E:E,Data!C:C,"Income",Data!D:D,"Mar") -> 740000 | C17: =SUMIFS(Data!F:F,Data!C:C,"Income",Data!D:D,"Mar") -> 772000 | D17: =C17-B17 -> 32000

Sheet Forecast
A1: BrewMetrics Coffee Co. — Q2 Rolling Forecast (Apr–Jun)
A2: Driver-based forecast off Q1 actuals. Blue = input assumptions; green = links to other tabs.
A4: Assumptions
A5: Revenue MoM Growth | B5: 0.03
A6: Opex MoM Growth | B6: 0.01
A7: COGS % of Revenue | B7: =Summary!C6/Summary!C5 -> 0.32815356
A8: Starting Revenue (Mar Act) | B8: =Data!F18 -> 772000
A9: Starting Opex (Mar Act) | B9: =SUMIFS(Data!F:F,Data!C:C,"Opex",Data!D:D,"Mar") -> 397500
A12: Line Item | B12: Apr | C12: May | D12: Jun | E12: Q2 Total | H12: Month | I12: Revenue | J12: Operating Income
A13: Revenue | B13: =B8*(1+$B$5) -> 795160 | C13: =B13*(1+$B$5) -> 819014.8 | D13: =C13*(1+$B$5) -> 843585.24 | E13: =SUM(B13:D13) -> 2457760 | H13: Apr | I13: =B13 -> 795160 | J13: =B17 -> 132750.41
A14: COGS | B14: =B13*$B$7 -> 260934.59 | C14: =C13*$B$7 -> 268762.63 | D14: =D13*$B$7 -> 276825.51 | E14: =SUM(B14:D14) -> 806522.72 | H14: May | I14: =C13 -> 819014.8 | J14: =C17 -> 144762.42
A15: Gross Profit | B15: =B13-B14 -> 534225.41 | C15: =C13-C14 -> 550252.17 | D15: =D13-D14 -> 566759.74 | E15: =SUM(B15:D15) -> 1651237.3 | H15: Jun | I15: =D13 -> 843585.24 | J15: =D17 -> 157215.09
A16: Operating Expenses | B16: =B9*(1+$B$6) -> 401475 | C16: =B16*(1+$B$6) -> 405489.75 | D16: =C16*(1+$B$6) -> 409544.65 | E16: =SUM(B16:D16) -> 1216509.4
A17: Operating Income | B17: =B15-B16 -> 132750.41 | C17: =C15-C16 -> 144762.42 | D17: =D15-D16 -> 157215.09 | E17: =SUM(B17:D17) -> 434727.93
A18: Operating Margin % | B18: =B17/B13 -> 0.16694805 | C18: =C17/C13 -> 0.1767519 | D18: =D17/D13 -> 0.18636539 | E18: =E17/E13 -> 0.17687973
